open3SPN2/3SPN2.conf
open3SPN2/3SPN2.xml
open3SPN2/DNA_atomic.csv
open3SPN2/__init__.py
open3SPN2/_version.py
open3SPN2/ff3SPN2.py
open3SPN2/function_terms.py
open3SPN2/geometry.py
open3SPN2-0.3.2.dist-info/LICENSE.txt
open3SPN2-0.3.2.dist-info/METADATA
open3SPN2-0.3.2.dist-info/WHEEL
open3SPN2-0.3.2.dist-info/top_level.txt
open3SPN2-0.3.2.dist-info/RECORD
