Metadata-Version: 2.1
Name: open3SPN2
Version: 0.3.2
Home-page: https://github.com/cabb99/open3spn2
Download-URL: https://github.com/cabb99/open3spn2/archive/0.2.0.tar.gz
Author: Carlos Bueno
Author-email: carlos.bueno@rice.edu
License: MIT
Keywords: dna,forcefield,openmm
Classifier: Development Status :: 3 - Alpha
Classifier: Intended Audience :: Science/Research
Classifier: Topic :: Scientific/Engineering :: Physics
Classifier: License :: OSI Approved :: MIT License
Classifier: Programming Language :: Python :: 3
Classifier: Programming Language :: Python :: 3.4
Classifier: Programming Language :: Python :: 3.5
Classifier: Programming Language :: Python :: 3.6
Classifier: Programming Language :: Python :: 3.7
License-File: LICENSE.txt
Requires-Dist: biopython
Requires-Dist: pandas
Requires-Dist: numpy
Requires-Dist: scipy
Requires-Dist: mdtraj
Requires-Dist: openmm
Requires-Dist: pdbfixer
Requires-Dist: nose
